rsklpr/__init__.py
rsklpr/kde_statsmodels_impl/__init__.py
rsklpr/kde_statsmodels_impl/bandwidths.py
rsklpr/kde_statsmodels_impl/kernel_base.py
rsklpr/kde_statsmodels_impl/kernel_density.py
rsklpr/kde_statsmodels_impl/kernels.py
rsklpr/kernels.py
rsklpr/rsklpr.py
rsklpr-2.0.0.dist-info/LICENSE
rsklpr-2.0.0.dist-info/METADATA
rsklpr-2.0.0.dist-info/WHEEL
rsklpr-2.0.0.dist-info/RECORD
