Metadata-Version: 2.1
Name: rsklpr
Version: 2.0.0
Summary: Implementation of the Robust Local Polynomial Regression with Similarity Kernel method
Home-page: https://github.com/yaniv-shulman/rsklpr
Keywords: statistics,robust statistics,regression,robust regression,local polynomial regression,machine learning,locally weighted regression
Author: Yaniv Shulman
Author-email: yaniv@shulman.info
Requires-Python: >=3.9
Classifier: Intended Audience :: Developers
Classifier: Intended Audience :: Science/Research
Classifier: License :: OSI Approved :: MIT License
Classifier: Programming Language :: Python :: 3
Classifier: Programming Language :: Python :: 3.9
Classifier: Programming Language :: Python :: 3.10
Classifier: Programming Language :: Python :: 3.11
Classifier: Programming Language :: Python :: 3.12
Classifier: Programming Language :: Python :: 3.13
Classifier: Topic :: Scientific/Engineering :: Artificial Intelligence
Classifier: Topic :: Scientific/Engineering :: Mathematics
Requires-Dist: joblib (>=1.4.2,<2.0.0)
Requires-Dist: numpy (>=2.0.2,<3.0.0)
Requires-Dist: scikit-learn (>=1.5.2,<2.0.0)
Requires-Dist: scipy (>=1.13.1,<2.0.0)
Project-URL: Repository, https://github.com/yaniv-shulman/rsklpr
